data/__init__.py
data/data_utils.py
dbs/__init__.py
models/__init__.py
models/tabela_execucoes.py
models/tabela_experimentos.py
models/tabela_modelos.py
src/__init__.py
src/classifier.py
src/classifierold.py
src/vectorizer.py
tests/__init__.py
utils/__init__.py
utils/result_visualizer.py
utils/utils.py
prodclass-0.1.1.dist-info/METADATA
prodclass-0.1.1.dist-info/WHEEL
prodclass-0.1.1.dist-info/top_level.txt
prodclass-0.1.1.dist-info/RECORD
