Metadata-Version: 2.1
Name: prodclass
Version: 0.1.1
Summary: Uma biblioteca Python para auxiliar na vetorização e categorização de descrições de produto.
Home-page: https://github.com/GHDaru/prodclass/tree/master
Author: Gilsiley Henrique Darú
Author-email: ghdaru@gmail.com
Classifier: Programming Language :: Python :: 3
Classifier: License :: OSI Approved :: MIT License
Classifier: Operating System :: OS Independent
Requires-Python: >=3.6
Requires-Dist: pandas >=1.2
Requires-Dist: numpy >=1.19
Requires-Dist: scikit-learn >=0.24
Requires-Dist: matplotlib >=3.3
Requires-Dist: seaborn >=0.11
Requires-Dist: statsmodels >=0.12
